src/__init__.py
src/phase1.py
src/phase2.py
src/phase3.py
src/rmedian.py
RMedian_Algorithm-0.0.1.dist-info/LICENSE
RMedian_Algorithm-0.0.1.dist-info/METADATA
RMedian_Algorithm-0.0.1.dist-info/WHEEL
RMedian_Algorithm-0.0.1.dist-info/top_level.txt
RMedian_Algorithm-0.0.1.dist-info/RECORD
