Metadata-Version: 2.1
Name: RMedian-Algorithm
Version: 0.0.1
Summary: Package for the RMedian algorithm
Home-page: https://github.com/jfklorenz/RMedian-Algorithm
Author: Julian Lorenz
Author-email: jfk.lorenz@gmail.com
License: UNKNOWN
Platform: UNKNOWN
Classifier: Programming Language :: Python :: 3
Classifier: License :: OSI Approved :: MIT License
Classifier: Operating System :: OS Independent
Requires-Python: >=3.6
